{"name":"Idle","SubTexture":[{"name":"元件 25","height":33,"x":0,"y":225,"width":101},{"name":"元件 20","height":121,"x":204,"y":0,"width":128},{"name":"元件 17","height":224,"x":0,"y":0,"width":203},{"name":"元件 16","height":30,"x":383,"y":188,"width":30},{"name":"元件 26","height":48,"x":247,"y":203,"width":41},{"name":"元件 15","height":39,"x":247,"y":252,"width":36},{"name":"元件 19","height":42,"x":300,"y":122,"width":30},{"name":"元件 24","height":24,"x":102,"y":258,"width":37},{"name":"元件 18","height":44,"x":383,"y":103,"width":32},{"name":"元件 22","height":44,"x":461,"y":249,"width":36},{"name":"元件 23","height":26,"x":370,"y":253,"width":38},{"name":"元件 21","height":45,"x":289,"y":224,"width":37},{"name":"元件 8","height":80,"x":204,"y":122,"width":94},{"name":"元件 6","height":60,"x":204,"y":203,"width":42},{"name":"元件 13","height":24,"x":300,"y":199,"width":25},{"name":"元件 12","height":30,"x":327,"y":253,"width":42},{"name":"元件 14","height":38,"x":383,"y":149,"width":30},{"name":"元件 7","height":32,"x":102,"y":225,"width":64},{"name":"元件 1","height":97,"x":417,"y":0,"width":83},{"name":"元件 2","height":102,"x":333,"y":0,"width":83},{"name":"元件 3","height":93,"x":415,"y":184,"width":44},{"name":"元件 4","height":93,"x":333,"y":103,"width":49},{"name":"元件 9","height":64,"x":461,"y":184,"width":50},{"name":"元件 11","height":33,"x":300,"y":165,"width":31},{"name":"元件 10","height":55,"x":332,"y":197,"width":47},{"name":"元件 5","height":85,"x":417,"y":98,"width":80}],"imagePath":"texture.png"}